<beans xmlns="http://www.springframework.org/schema/beans"
       xmlns:xsi="http://www.w3.org/2001/XMLSchema-instance"
       xsi:schemaLocation="http://www.springframework.org/schema/beans http://www.springframework.org/schema/beans/spring-beans.xsd">

    <bean id="metricsTaskServer" class="ru.taskurotta.server.MetricsTaskServer">
        <constructor-arg name="taskServer" ref="realTaskServer"/>
        <constructor-arg name="metricsFactory" ref="metricsFactory"/>
        <constructor-arg name="numberDataListener" ref="metricsNumberDataHandler" />
        <constructor-arg name="metricsPeriodSeconds" value = "${metric.data.memory.period-in-seconds}" />
    </bean>

    <bean id="taskServer" class="ru.taskurotta.assemble.ProxyTaskServer">
        <constructor-arg name="target" ref="metricsTaskServer" />
    </bean>

    <bean id="metricsFactory" class="ru.taskurotta.service.statistics.MetricsFactory" destroy-method="shutdown">
        <constructor-arg name="dumpPeriod" value="${metric.data.method.period-in-seconds}"/>
        <constructor-arg name="dumpingThreads" value="3"/>
        <constructor-arg name="dataListener" ref="metricsDataHandler"/>
    </bean>

    <bean id="metricsDataHandler" class="ru.taskurotta.service.statistics.MetricsDataHandler" init-method="init"/>
    <bean id="metricsNumberDataHandler" class="ru.taskurotta.service.statistics.NumberDataHandler" init-method="init"/>

</beans>